setup.py
tests/__init__.py
tests/test_TimefileHandler.py
timefile_handler/__init__.py
timefile_handler/handler.py
timefile_logging_handler.egg-info/PKG-INFO
timefile_logging_handler.egg-info/SOURCES.txt
timefile_logging_handler.egg-info/dependency_links.txt
timefile_logging_handler.egg-info/top_level.txt