Metadata-Version: 1.1
Name: timefile-logging-handler
Version: 1.0.0
Summary: Log file with datetime
Home-page: https://github.com/yaxin-cn/timefile-logging-handeler
Author: yaxin
Author-email: yaxin.me@gmail.com
License: MIT
Platform: UNKNOWN
Classifier: Development Status :: 5 - Production/Stable
Classifier: Intended Audience :: Developers
Classifier: Programming Language :: Python :: 2.7
Classifier: Programming Language :: Python :: 3
